tkp_finder/__about__.py
tkp_finder/__init__.py
tkp_finder/deeptm.py
tkp_finder/tkp_finder.py
tkp_finder-0.2.dist-info/METADATA
tkp_finder-0.2.dist-info/WHEEL
tkp_finder-0.2.dist-info/entry_points.txt
tkp_finder-0.2.dist-info/licenses/LICENSE.txt
tkp_finder-0.2.dist-info/RECORD
