Metadata-Version: 2.1
Name: tkp-finder
Version: 0.2
Summary: A tool to discover and annotate tandem protein kinases
Project-URL: Documentation, https://github.com/edikedik/tkp-finder#readme
Project-URL: Issues, https://github.com/edikedik/tkp-finder/issues
Project-URL: Source, https://github.com/edikedik/tkp-finder
Author-email: Ivan Reveguk <edikedikedikedik@gmail.com>
License-File: LICENSE.txt
Classifier: Development Status :: 4 - Beta
Classifier: Programming Language :: Python
Classifier: Programming Language :: Python :: 3.10
Classifier: Programming Language :: Python :: 3.11
Classifier: Programming Language :: Python :: Implementation :: CPython
Requires-Python: >=3.10
Requires-Dist: click>=8
Requires-Dist: lxtractor
Requires-Dist: more-itertools>=9.0
Requires-Dist: pandas>=1.5
Requires-Dist: pybiolib>=1.1.700
Requires-Dist: toolz>=0.12
Requires-Dist: tqdm>=4.64
